nectarallocationclient/__init__.py
nectarallocationclient/base.py
nectarallocationclient/client.py
nectarallocationclient/exceptions.py
nectarallocationclient/states.py
nectarallocationclient/osc/__init__.py
nectarallocationclient/osc/plugin.py
nectarallocationclient/osc/utils.py
nectarallocationclient/osc/v1/__init__.py
nectarallocationclient/osc/v1/allocations.py
nectarallocationclient/osc/v1/bundles.py
nectarallocationclient/osc/v1/facilities.py
nectarallocationclient/osc/v1/grants.py
nectarallocationclient/osc/v1/organisations.py
nectarallocationclient/osc/v1/quotas.py
nectarallocationclient/osc/v1/resources.py
nectarallocationclient/osc/v1/service_types.py
nectarallocationclient/osc/v1/sites.py
nectarallocationclient/osc/v1/zones.py
nectarallocationclient/tests/__init__.py
nectarallocationclient/tests/unit/__init__.py
nectarallocationclient/tests/unit/fakes.py
nectarallocationclient/tests/unit/utils.py
nectarallocationclient/tests/unit/v1/__init__.py
nectarallocationclient/tests/unit/v1/fakes.py
nectarallocationclient/tests/unit/v1/test_allocations.py
nectarallocationclient/tests/unit/v1/test_bundles.py
nectarallocationclient/tests/unit/v1/test_facilities.py
nectarallocationclient/tests/unit/v1/test_organisations.py
nectarallocationclient/tests/unit/v1/test_quotas.py
nectarallocationclient/tests/unit/v1/test_resources.py
nectarallocationclient/tests/unit/v1/test_sites.py
nectarallocationclient/tests/unit/v1/test_zones.py
nectarallocationclient/v1/__init__.py
nectarallocationclient/v1/allocations.py
nectarallocationclient/v1/bundles.py
nectarallocationclient/v1/chiefinvestigators.py
nectarallocationclient/v1/client.py
nectarallocationclient/v1/facilities.py
nectarallocationclient/v1/grants.py
nectarallocationclient/v1/organisations.py
nectarallocationclient/v1/publications.py
nectarallocationclient/v1/quotas.py
nectarallocationclient/v1/resources.py
nectarallocationclient/v1/service_types.py
nectarallocationclient/v1/sites.py
nectarallocationclient/v1/zones.py
nectarallocationclient-2.0.0.dist-info/LICENSE
nectarallocationclient-2.0.0.dist-info/METADATA
nectarallocationclient-2.0.0.dist-info/WHEEL
nectarallocationclient-2.0.0.dist-info/entry_points.txt
nectarallocationclient-2.0.0.dist-info/pbr.json
nectarallocationclient-2.0.0.dist-info/top_level.txt
nectarallocationclient-2.0.0.dist-info/RECORD
