Metadata-Version: 2.1
Name: nectarallocationclient
Version: 2.0.0
Summary: Client for the Nectar Allocation system
Home-page: https://github.com/NeCTAR-RC/python-nectarallocationclient
Author: ARDC Nectar Cloud Services
Author-email: coreservices@ardc.edu.au
License: Apache-2.0
Keywords: nectarallocation
Classifier: Environment :: OpenStack
Classifier: Intended Audience :: Information Technology
Classifier: Intended Audience :: System Administrators
Classifier: License :: OSI Approved :: Apache Software License
Classifier: Operating System :: POSIX :: Linux
Classifier: Programming Language :: Python
Classifier: Programming Language :: Python :: 3 :: Only
Classifier: Programming Language :: Python :: 3
Classifier: Programming Language :: Python :: 3.10
Classifier: Programming Language :: Python :: 3.12
License-File: LICENSE
Requires-Dist: oslo.utils
Requires-Dist: requests
Requires-Dist: keystoneauth1
Requires-Dist: osc-lib
Requires-Dist: pbr
